pymethylation_utils/__init__.py
pymethylation_utils/utils.py
pymethylation_utils/bin/epimetheus
tests/__init__.py
tests/test_run_methylation_utils.py
pymethylation_utils-0.5.3.dist-info/LICENSE
pymethylation_utils-0.5.3.dist-info/METADATA
pymethylation_utils-0.5.3.dist-info/WHEEL
pymethylation_utils-0.5.3.dist-info/top_level.txt
pymethylation_utils-0.5.3.dist-info/RECORD
