Metadata-Version: 2.2
Name: pymethylation_utils
Version: 0.5.3
Summary: Python wrapper for the epimetheus Rust binary
Author: Sebastian Dall
Author-email: semoda@bio.aau.dk
License-File: LICENSE
Dynamic: author
Dynamic: author-email
Dynamic: summary
